<?xml version="1.0" encoding="UTF-8"?>
<meta xmlns="http://exist-db.org/xquery/repo">
    <description>Store API for annotatorjs.org implemented as eXist-db library.</description>
    <author>Benjamin W. Bohl</author>
    <author>Mathias Göbel</author>
    <author>Ubbo Veentjer</author>
    <website>http://www.github.com/DARIAH-DE/eXanore</website>
    <status>beta</status>
    <license>GNU-GPL 3.0</license>
    <copyright>true</copyright>
    <type>library</type>
    <target>eXanore</target>
    <prepare>pre-install.xql</prepare>
    <finish/>
    <permissions user="admin" group="dba" mode="rwxrwxr--"/>
</meta>
